openinference/instrumentation/pydantic_ai/__init__.py
openinference/instrumentation/pydantic_ai/package.py
openinference/instrumentation/pydantic_ai/py.typed
openinference/instrumentation/pydantic_ai/semantic_conventions.py
openinference/instrumentation/pydantic_ai/span_processor.py
openinference/instrumentation/pydantic_ai/utils.py
openinference/instrumentation/pydantic_ai/version.py
openinference_instrumentation_pydantic_ai-0.1.10.dist-info/METADATA
openinference_instrumentation_pydantic_ai-0.1.10.dist-info/WHEEL
openinference_instrumentation_pydantic_ai-0.1.10.dist-info/licenses/LICENSE
openinference_instrumentation_pydantic_ai-0.1.10.dist-info/RECORD
